friday_pulse/__init__.py
friday_pulse/client.py
friday_pulse/responses.py
friday_pulse-0.1.0.dist-info/METADATA
friday_pulse-0.1.0.dist-info/WHEEL
friday_pulse-0.1.0.dist-info/RECORD
